python_eicar/__init__.py
python_eicar/main.py
python_eicar-0.1.1.dist-info/licenses/LICENSE
python_eicar-0.1.1.dist-info/METADATA
python_eicar-0.1.1.dist-info/WHEEL
python_eicar-0.1.1.dist-info/entry_points.txt
python_eicar-0.1.1.dist-info/top_level.txt
python_eicar-0.1.1.dist-info/RECORD
