Metadata-Version: 2.4
Name: python_eicar
Version: 0.1.1
Summary: EICAR test string utility for AV detection testing
Home-page: https://github.com/khalidwalidalamri/python-eicar
License: MIT
License-File: LICENSE
Dynamic: description
Dynamic: description-content-type
Dynamic: home-page
Dynamic: license
Dynamic: license-file
Dynamic: summary
